math_calculator/__init__.py
math_calculator/core.py
CHADs_calculator-0.1.dist-info/LICENSE
CHADs_calculator-0.1.dist-info/METADATA
CHADs_calculator-0.1.dist-info/WHEEL
CHADs_calculator-0.1.dist-info/top_level.txt
CHADs_calculator-0.1.dist-info/RECORD
