Metadata-Version: 2.1
Name: CHADs-calculator
Version: 0.1
Summary: A simple calculator library for basic arithmetic operations.
Author: Vlad_Chad
Author-email: 3336096509@qq.com
Classifier: Programming Language :: Python :: 3
Classifier: License :: OSI Approved :: MIT License
Classifier: Operating System :: OS Independent
License-File: LICENSE
